psf/__init__.py
psf/jivrtt/__init__.py
psf/jivrtt/csv/__init__.py
psf/jivrtt/csv/egress.py
psf/jivrtt/csv/ingress.py
psf/jivrtt/csv/source.py
psf/jivrtt/flow/__init__.py
psf/jivrtt/flow/base.py
psf/jivrtt/flow/dist.py
psf/jivrtt/flow/flow.py
psf/jivrtt/flow/log.py
psf/jivrtt/flow/run.py
py_simple_flow-2020.8.23.3.dist-info/METADATA
py_simple_flow-2020.8.23.3.dist-info/WHEEL
py_simple_flow-2020.8.23.3.dist-info/top_level.txt
py_simple_flow-2020.8.23.3.dist-info/RECORD
