Metadata-Version: 2.1
Name: py-simple-flow
Version: 2020.8.23.3
Summary: Simple data processing (ETL) library with support for multi-processing
Home-page: UNKNOWN
Author: Nikhil K Madhusudhan (nikhilkmdev)
Author-email: nikhilkmdev@gmail.com
Maintainer: Nikhil K Madhusudhan (nikhilkmdev)
Maintainer-email: nikhilkmdev@gmail.com
License: MIT
Keywords: etl,multi processing,data,processing,data processing,data flow,python3
Platform: UNKNOWN
Classifier: License :: OSI Approved :: MIT License
Classifier: Programming Language :: Python :: 3
Classifier: Programming Language :: Python :: 3.7
Requires-Dist: pandas
